tools/__init__.py
tools/my_tool/__init__.py
tools/my_tool/handler.py
tools/watch_query/__init__.py
tools/watch_query/handler.py
tools/watch_query/manifest.json
watch_mcp_core/__init__.py
watch_mcp_core/mcp_server_watch.py
watch_mcp_core-2.0.1.dist-info/METADATA
watch_mcp_core-2.0.1.dist-info/WHEEL
watch_mcp_core-2.0.1.dist-info/entry_points.txt
watch_mcp_core-2.0.1.dist-info/top_level.txt
watch_mcp_core-2.0.1.dist-info/RECORD
